Workbook

Sheet Data
B1: Minorista | C1: ID Minorista | D1: Fecha de Factura | E1: Region | F1: Estado | G1: Ciudad | H1: Producto | I1: Precio por Unidad | J1: Unidades Vendidas | K1: Ventas Totales | L1: Ganancia Operativa | M1: Margen Operativo | N1: Metodo de Venta | O1: Metodo de Pago | P1: Tipo de Cliente
B2: Foot Locker | C2: 1185732 | D2: 43831 | E2: Northeast | F2: New York | G2: New York | H2: Men's Street Footwear | I2: 50 | J2: 1200 | K2: 600000 | L2: 300000 | M2: 0.5 | N2: In-store | O2: Transferencia bancaria | P2: Nuevo
B3: Foot Locker | C3: 1185732 | D3: 43832 | E3: Northeast | F3: New York | G3: New York | H3: Men's Athletic Footwear | I3: 50 | J3: 1000 | K3: 500000 | L3: 150000 | M3: 0.3 | N3: In-store | O3: Tarjeta | P3: Recurrente
B4: Foot Locker | C4: 1185732 | D4: 43833 | E4: Northeast | F4: New York | G4: New York | H4: Women's Street Footwear | I4: 40 | J4: 1000 | K4: 400000 | L4: 140000 | M4: 0.35 | N4: In-store | O4: Tarjeta | P4: Recurrente
B5: Foot Locker | C5: 1185732 | D5: 43834 | E5: Northeast | F5: New York | G5: New York | H5: Women's Athletic Footwear | I5: 45 | J5: 850 | K5: 382500 | L5: 133875 | M5: 0.35 | N5: In-store | O5: Tarjeta | P5: Nuevo
B6: Foot Locker | C6: 1185732 | D6: 43835 | E6: Northeast | F6: New York | G6: New York | H6: Men's Apparel | I6: 60 | J6: 900 | K6: 540000 | L6: 162000 | M6: 0.3 | N6: In-store | O6: Transferencia bancaria | P6: Recurrente
B7: Foot Locker | C7: 1185732 | D7: 43836 | E7: Northeast | F7: New York | G7: New York | H7: Women's Apparel | I7: 50 | J7: 1000 | K7: 500000 | L7: 125000 | M7: 0.25 | N7: In-store | O7: Efectivo | P7: Recurrente
B8: Foot Locker | C8: 1185732 | D8: 43837 | E8: Northeast | F8: New York | G8: New York | H8: Men's Street Footwear | I8: 50 | J8: 1250 | K8: 625000 | L8: 312500 | M8: 0.5 | N8: In-store | O8: Efectivo | P8: Recurrente
B9: Foot Locker | C9: 1185732 | D9: 43838 | E9: Northeast | F9: New York | G9: New York | H9: Men's Athletic Footwear | I9: 50 | J9: 900 | K9: 450000 | L9: 135000 | M9: 0.3 | N9: Outlet | O9: Efectivo | P9: Recurrente
B10: Foot Locker | C10: 1185732 | D10: 43851 | E10: Northeast | F10: New York | G10: New York | H10: Women's Street Footwear | I10: 40 | J10: 950 | K10: 380000 | L10: 133000 | M10: 0.35 | N10: Outlet | O10: Tarjeta | P10: Recurrente
B11: Foot Locker | C11: 1185732 | D11: 43852 | E11: Northeast | F11: New York | G11: New York | H11: Women's Athletic Footwear | I11: 45 | J11: 825 | K11: 371250 | L11: 129937.5 | M11: 0.35 | N11: Outlet | O11: Efectivo | P11: Recurrente
B12: Foot Locker | C12: 1185732 | D12: 43853 | E12: Northeast | F12: New York | G12: New York | H12: Men's Apparel | I12: 60 | J12: 900 | K12: 540000 | L12: 162000 | M12: 0.3 | N12: Outlet | O12: Tarjeta | P12: Recurrente
B13: Foot Locker | C13: 1185732 | D13: 43854 | E13: Northeast | F13: New York | G13: New York | H13: Women's Apparel | I13: 50 | J13: 1000 | K13: 500000 | L13: 125000 | M13: 0.25 | N13: Outlet | O13: Tarjeta | P13: Recurrente
... B9649: Foot Locker | C9649: 1185732 | D9649: 44249 | E9649: Northeast | F9649: New Hampshire | G9649: Manchester | H9649: Women's Street Footwear | I9649: 29 | J9649: 83 | K9649: 2407 | L9649: 649.89 | M9649: 0.27 | N9649: Outlet | O9649: Transferencia bancaria | P9649: Recurrente

Sheet Producto
A1: ID Producto | B1: Producto
A2: 1 | B2: {=UNIQUE(Data!H2:H1000)} -> Men's Street Footwear
A3: 2 | B3: Men's Athletic Footwear
A4: 3 | B4: Women's Street Footwear
A5: 4 | B5: Women's Athletic Footwear
A6: 5 | B6: Men's Apparel
A7: 6 | B7: Women's Apparel

Sheet Ubicacion
A1: Llave_Aux | B1: ID Ubicacion | C1: Region | D1: Estado | E1: Ciudad
A2: =C2&D2&E2 -> NortheastNew YorkNew York | B2: 1 | C2: {=UNIQUE(Data!E2:G2168)} -> Northeast | D2: New York | E2: New York
A3: =C3&D3&E3 -> SouthTexasHouston | B3: 2 | C3: South | D3: Texas | E3: Houston
A4: =C4&D4&E4 -> WestCaliforniaSan Francisco | B4: 3 | C4: West | D4: California | E4: San Francisco
A5: =C5&D5&E5 -> WestCaliforniaLos Angeles | B5: 4 | C5: West | D5: California | E5: Los Angeles
A6: =C6&D6&E6 -> MidwestIllinoisChicago | B6: 5 | C6: Midwest | D6: Illinois | E6: Chicago
A7: =C7&D7&E7 -> SouthTexasDallas | B7: 6 | C7: South | D7: Texas | E7: Dallas
A8: =C8&D8&E8 -> NortheastPennsylvaniaPhiladelphia | B8: 7 | C8: Northeast | D8: Pennsylvania | E8: Philadelphia
A9: =C9&D9&E9 -> WestNevadaLas Vegas | B9: 8 | C9: West | D9: Nevada | E9: Las Vegas
A10: =C10&D10&E10 -> WestColoradoDenver | B10: 9 | C10: West | D10: Colorado | E10: Denver
A11: =C11&D11&E11 -> WestWashingtonSeattle | B11: 10 | C11: West | D11: Washington | E11: Seattle
A12: =C12&D12&E12 -> SoutheastFloridaMiami | B12: 11 | C12: Southeast | D12: Florida | E12: Miami
A13: =C13&D13&E13 -> MidwestMinnesotaMinneapolis | B13: 12 | C13: Midwest | D13: Minnesota | E13: Minneapolis
A14: =C14&D14&E14 -> MidwestMontanaBillings | B14: 13 | C14: Midwest | D14: Montana | E14: Billings
... A55: =C55&D55&E55 -> NortheastNew HampshireManchester | B55: 54 | C55: Northeast | D55: New Hampshire | E55: Manchester

Sheet Minorista
A1: Minorista | B1: ID Minorista
A2: {=UNIQUE(Data!B2:B1000)} -> Foot Locker | B2: 1
A3: Walmart | B3: 2
A4: Sports Direct | B4: 3
A5: West Gear | B5: 4
A6: Kohl's | B6: 5
A7: Amazon | B7: 6

Sheet Fecha
A2: ID Fecha | B2: Año | C2: Mes | D2: Dia | E2: Dia de la Semana
A3: 43831 | B3: =YEAR(A3) -> 2020 | C3: =MONTH(A3) -> 1 | D3: =DAY(A3) -> 1 | E3: =TEXT(A3,"dddd") -> miércoles
A4: 43832 | B4: =YEAR(A4) -> 2020 | C4: =MONTH(A4) -> 1 | D4: =DAY(A4) -> 2 | E4: =TEXT(A4,"dddd") -> jueves
A5: 43833 | B5: =YEAR(A5) -> 2020 | C5: =MONTH(A5) -> 1 | D5: =DAY(A5) -> 3 | E5: =TEXT(A5,"dddd") -> viernes
A6: 43834 | B6: =YEAR(A6) -> 2020 | C6: =MONTH(A6) -> 1 | D6: =DAY(A6) -> 4 | E6: =TEXT(A6,"dddd") -> sábado
A7: 43835 | B7: =YEAR(A7) -> 2020 | C7: =MONTH(A7) -> 1 | D7: =DAY(A7) -> 5 | E7: =TEXT(A7,"dddd") -> domingo
A8: 43836 | B8: =YEAR(A8) -> 2020 | C8: =MONTH(A8) -> 1 | D8: =DAY(A8) -> 6 | E8: =TEXT(A8,"dddd") -> lunes
A9: 43837 | B9: =YEAR(A9) -> 2020 | C9: =MONTH(A9) -> 1 | D9: =DAY(A9) -> 7 | E9: =TEXT(A9,"dddd") -> martes
A10: 43838 | B10: =YEAR(A10) -> 2020 | C10: =MONTH(A10) -> 1 | D10: =DAY(A10) -> 8 | E10: =TEXT(A10,"dddd") -> miércoles
A11: 43851 | B11: =YEAR(A11) -> 2020 | C11: =MONTH(A11) -> 1 | D11: =DAY(A11) -> 21 | E11: =TEXT(A11,"dddd") -> martes
A12: 43852 | B12: =YEAR(A12) -> 2020 | C12: =MONTH(A12) -> 1 | D12: =DAY(A12) -> 22 | E12: =TEXT(A12,"dddd") -> miércoles
A13: 43853 | B13: =YEAR(A13) -> 2020 | C13: =MONTH(A13) -> 1 | D13: =DAY(A13) -> 23 | E13: =TEXT(A13,"dddd") -> jueves
A14: 43854 | B14: =YEAR(A14) -> 2020 | C14: =MONTH(A14) -> 1 | D14: =DAY(A14) -> 24 | E14: =TEXT(A14,"dddd") -> viernes
... A726: 44291 | B726: =YEAR(A726) -> 2021 | C726: =MONTH(A726) -> 4 | D726: =DAY(A726) -> 5 | E726: =TEXT(A726,"dddd") -> lunes

Sheet Ventas
A1: ID Ventas | B1: ID Fecha | C1: ID Minorista | D1: ID Producto | E1: ID Ubicacion | F1: Unidades Vendidas | G1: Precio por Unidad | H1: Ventas Totales | I1: Ganancia Operativa | J1: Metodo de Venta | K1: Metodo de Pago | L1: Tipo de Cliente
A2: 1 | B2: =Data!D2 -> 43831 | C2: =IFERROR(VLOOKUP(Data!B2, Minorista!$A$2:$B$100, 2, FALSE), "") -> 1 | D2: {=INDEX(Producto!$A$2:$A$500, MATCH(Data!H2, Producto!$B$2:$B$500, 0))} -> 1 | E2: =VLOOKUP(Data!E2 & Data!F2 & Data!G2, Ubicacion!$A$2:$B$1000, 2, FALSE) -> 1 | F2: =Data!J2 -> 1200 | G2: =Data!I2 -> 50 | H2: =Data!K2 -> 600000 | I2: =Data!L2 -> 300000 | J2: =Data!N2 -> In-store | K2: =Data!O2 -> Transferencia bancaria | L2: =Data!P2 -> Nuevo
A3: 2 | B3: =Data!D3 -> 43832 | C3: =IFERROR(VLOOKUP(Data!B3, Minorista!$A$2:$B$100, 2, FALSE), "") -> 1 | D3: {=INDEX(Producto!$A$2:$A$500, MATCH(Data!H3, Producto!$B$2:$B$500, 0))} -> 2 | E3: =VLOOKUP(Data!E3 & Data!F3 & Data!G3, Ubicacion!$A$2:$B$1000, 2, FALSE) -> 1 | F3: =Data!J3 -> 1000 | G3: =Data!I3 -> 50 | H3: =Data!K3 -> 500000 | I3: =Data!L3 -> 150000 | J3: =Data!N3 -> In-store | K3: =Data!O3 -> Tarjeta | L3: =Data!P3 -> Recurrente
A4: 3 | B4: =Data!D4 -> 43833 | C4: =IFERROR(VLOOKUP(Data!B4, Minorista!$A$2:$B$100, 2, FALSE), "") -> 1 | D4: {=INDEX(Producto!$A$2:$A$500, MATCH(Data!H4, Producto!$B$2:$B$500, 0))} -> 3 | E4: =VLOOKUP(Data!E4 & Data!F4 & Data!G4, Ubicacion!$A$2:$B$1000, 2, FALSE) -> 1 | F4: =Data!J4 -> 1000 | G4: =Data!I4 -> 40 | H4: =Data!K4 -> 400000 | I4: =Data!L4 -> 140000 | J4: =Data!N4 -> In-store | K4: =Data!O4 -> Tarjeta | L4: =Data!P4 -> Recurrente
A5: 4 | B5: =Data!D5 -> 43834 | C5: =IFERROR(VLOOKUP(Data!B5, Minorista!$A$2:$B$100, 2, FALSE), "") -> 1 | D5: {=INDEX(Producto!$A$2:$A$500, MATCH(Data!H5, Producto!$B$2:$B$500, 0))} -> 4 | E5: =VLOOKUP(Data!E5 & Data!F5 & Data!G5, Ubicacion!$A$2:$B$1000, 2, FALSE) -> 1 | F5: =Data!J5 -> 850 | G5: =Data!I5 -> 45 | H5: =Data!K5 -> 382500 | I5: =Data!L5 -> 133875 | J5: =Data!N5 -> In-store | K5: =Data!O5 -> Tarjeta | L5: =Data!P5 -> Nuevo
A6: 5 | B6: =Data!D6 -> 43835 | C6: =IFERROR(VLOOKUP(Data!B6, Minorista!$A$2:$B$100, 2, FALSE), "") -> 1 | D6: {=INDEX(Producto!$A$2:$A$500, MATCH(Data!H6, Producto!$B$2:$B$500, 0))} -> 5 | E6: =VLOOKUP(Data!E6 & Data!F6 & Data!G6, Ubicacion!$A$2:$B$1000, 2, FALSE) -> 1 | F6: =Data!J6 -> 900 | G6: =Data!I6 -> 60 | H6: =Data!K6 -> 540000 | I6: =Data!L6 -> 162000 | J6: =Data!N6 -> In-store | K6: =Data!O6 -> Transferencia bancaria | L6: =Data!P6 -> Recurrente
A7: 6 | B7: =Data!D7 -> 43836 | C7: =IFERROR(VLOOKUP(Data!B7, Minorista!$A$2:$B$100, 2, FALSE), "") -> 1 | D7: {=INDEX(Producto!$A$2:$A$500, MATCH(Data!H7, Producto!$B$2:$B$500, 0))} -> 6 | E7: =VLOOKUP(Data!E7 & Data!F7 & Data!G7, Ubicacion!$A$2:$B$1000, 2, FALSE) -> 1 | F7: =Data!J7 -> 1000 | G7: =Data!I7 -> 50 | H7: =Data!K7 -> 500000 | I7: =Data!L7 -> 125000 | J7: =Data!N7 -> In-store | K7: =Data!O7 -> Efectivo | L7: =Data!P7 -> Recurrente
A8: 7 | B8: =Data!D8 -> 43837 | C8: =IFERROR(VLOOKUP(Data!B8, Minorista!$A$2:$B$100, 2, FALSE), "") -> 1 | D8: {=INDEX(Producto!$A$2:$A$500, MATCH(Data!H8, Producto!$B$2:$B$500, 0))} -> 1 | E8: =VLOOKUP(Data!E8 & Data!F8 & Data!G8, Ubicacion!$A$2:$B$1000, 2, FALSE) -> 1 | F8: =Data!J8 -> 1250 | G8: =Data!I8 -> 50 | H8: =Data!K8 -> 625000 | I8: =Data!L8 -> 312500 | J8: =Data!N8 -> In-store | K8: =Data!O8 -> Efectivo | L8: =Data!P8 -> Recurrente
A9: 8 | B9: =Data!D9 -> 43838 | C9: =IFERROR(VLOOKUP(Data!B9, Minorista!$A$2:$B$100, 2, FALSE), "") -> 1 | D9: {=INDEX(Producto!$A$2:$A$500, MATCH(Data!H9, Producto!$B$2:$B$500, 0))} -> 2 | E9: =VLOOKUP(Data!E9 & Data!F9 & Data!G9, Ubicacion!$A$2:$B$1000, 2, FALSE) -> 1 | F9: =Data!J9 -> 900 | G9: =Data!I9 -> 50 | H9: =Data!K9 -> 450000 | I9: =Data!L9 -> 135000 | J9: =Data!N9 -> Outlet | K9: =Data!O9 -> Efectivo | L9: =Data!P9 -> Recurrente
A10: 9 | B10: =Data!D10 -> 43851 | C10: =IFERROR(VLOOKUP(Data!B10, Minorista!$A$2:$B$100, 2, FALSE), "") -> 1 | D10: {=INDEX(Producto!$A$2:$A$500, MATCH(Data!H10, Producto!$B$2:$B$500, 0))} -> 3 | E10: =VLOOKUP(Data!E10 & Data!F10 & Data!G10, Ubicacion!$A$2:$B$1000, 2, FALSE) -> 1 | F10: =Data!J10 -> 950 | G10: =Data!I10 -> 40 | H10: =Data!K10 -> 380000 | I10: =Data!L10 -> 133000 | J10: =Data!N10 -> Outlet | K10: =Data!O10 -> Tarjeta | L10: =Data!P10 -> Recurrente
A11: 10 | B11: =Data!D11 -> 43852 | C11: =IFERROR(VLOOKUP(Data!B11, Minorista!$A$2:$B$100, 2, FALSE), "") -> 1 | D11: {=INDEX(Producto!$A$2:$A$500, MATCH(Data!H11, Producto!$B$2:$B$500, 0))} -> 4 | E11: =VLOOKUP(Data!E11 & Data!F11 & Data!G11, Ubicacion!$A$2:$B$1000, 2, FALSE) -> 1 | F11: =Data!J11 -> 825 | G11: =Data!I11 -> 45 | H11: =Data!K11 -> 371250 | I11: =Data!L11 -> 129937.5 | J11: =Data!N11 -> Outlet | K11: =Data!O11 -> Efectivo | L11: =Data!P11 -> Recurrente
A12: 11 | B12: =Data!D12 -> 43853 | C12: =IFERROR(VLOOKUP(Data!B12, Minorista!$A$2:$B$100, 2, FALSE), "") -> 1 | D12: {=INDEX(Producto!$A$2:$A$500, MATCH(Data!H12, Producto!$B$2:$B$500, 0))} -> 5 | E12: =VLOOKUP(Data!E12 & Data!F12 & Data!G12, Ubicacion!$A$2:$B$1000, 2, FALSE) -> 1 | F12: =Data!J12 -> 900 | G12: =Data!I12 -> 60 | H12: =Data!K12 -> 540000 | I12: =Data!L12 -> 162000 | J12: =Data!N12 -> Outlet | K12: =Data!O12 -> Tarjeta | L12: =Data!P12 -> Recurrente
A13: 12 | B13: =Data!D13 -> 43854 | C13: =IFERROR(VLOOKUP(Data!B13, Minorista!$A$2:$B$100, 2, FALSE), "") -> 1 | D13: {=INDEX(Producto!$A$2:$A$500, MATCH(Data!H13, Producto!$B$2:$B$500, 0))} -> 6 | E13: =VLOOKUP(Data!E13 & Data!F13 & Data!G13, Ubicacion!$A$2:$B$1000, 2, FALSE) -> 1 | F13: =Data!J13 -> 1000 | G13: =Data!I13 -> 50 | H13: =Data!K13 -> 500000 | I13: =Data!L13 -> 125000 | J13: =Data!N13 -> Outlet | K13: =Data!O13 -> Tarjeta | L13: =Data!P13 -> Recurrente
... A9649: 9648 | B9649: =Data!D9649 -> 44249 | C9649: =IFERROR(VLOOKUP(Data!B9649, Minorista!$A$2:$B$100, 2, FALSE), "") -> 1 | D9649: {=INDEX(Producto!$A$2:$A$500, MATCH(Data!H9649, Producto!$B$2:$B$500, 0))} -> 3 | E9649: =VLOOKUP(Data!E9649 & Data!F9649 & Data!G9649, Ubicacion!$A$2:$B$1000, 2, FALSE) -> 54 | F9649: =Data!J9649 -> 83 | G9649: =Data!I9649 -> 29 | H9649: =Data!K9649 -> 2407 | I9649: =Data!L9649 -> 649.89 | J9649: =Data!N9649 -> Outlet | K9649: =Data!O9649 -> Transferencia bancaria | L9649: =Data!P9649 -> Recurrente
B9650: =Data!D9650 | C9650: =IFERROR(VLOOKUP(Data!B9650, Minorista!$A$2:$B$100, 2, FALSE), "") | D9650: {=INDEX(Producto!$A$2:$A$500, MATCH(Data!H9650, Producto!$B$2:$B$500, 0))} -> #N/A | E9650: =VLOOKUP(Data!E9650 & Data!F9650 & Data!G9650, Ubicacion!$A$2:$B$1000, 2, FALSE) -> #N/A | F9650: =Data!J9650 | G9650: =Data!I9650 | H9650: =Data!K9650 | I9650: =Data!L9650 | J9650: =Data!N9650 | K9650: =Data!O9650 | L9650: =Data!P9650
B9651: =Data!D9651 | C9651: =IFERROR(VLOOKUP(Data!B9651, Minorista!$A$2:$B$100, 2, FALSE), "") | D9651: {=INDEX(Producto!$A$2:$A$500, MATCH(Data!H9651, Producto!$B$2:$B$500, 0))} -> #N/A | E9651: =VLOOKUP(Data!E9651 & Data!F9651 & Data!G9651, Ubicacion!$A$2:$B$1000, 2, FALSE) -> #N/A | F9651: =Data!J9651 | G9651: =Data!I9651 | H9651: =Data!K9651 | I9651: =Data!L9651 | J9651: =Data!N9651 | K9651: =Data!O9651 | L9651: =Data!P9651
B9652: =Data!D9652 | C9652: =IFERROR(VLOOKUP(Data!B9652, Minorista!$A$2:$B$100, 2, FALSE), "") | D9652: {=INDEX(Producto!$A$2:$A$500, MATCH(Data!H9652, Producto!$B$2:$B$500, 0))} -> #N/A | E9652: =VLOOKUP(Data!E9652 & Data!F9652 & Data!G9652, Ubicacion!$A$2:$B$1000, 2, FALSE) -> #N/A | F9652: =Data!J9652 | G9652: =Data!I9652 | H9652: =Data!K9652 | I9652: =Data!L9652 | J9652: =Data!N9652 | K9652: =Data!O9652 | L9652: =Data!P9652
B9653: =Data!D9653 | C9653: =IFERROR(VLOOKUP(Data!B9653, Minorista!$A$2:$B$100, 2, FALSE), "") | D9653: {=INDEX(Producto!$A$2:$A$500, MATCH(Data!H9653, Producto!$B$2:$B$500, 0))} -> #N/A | E9653: =VLOOKUP(Data!E9653 & Data!F9653 & Data!G9653, Ubicacion!$A$2:$B$1000, 2, FALSE) -> #N/A | F9653: =Data!J9653 | G9653: =Data!I9653 | H9653: =Data!K9653 | I9653: =Data!L9653 | J9653: =Data!N9653 | K9653: =Data!O9653 | L9653: =Data!P9653
